tracardi_smtp_connector/plugin.py
tracardi_smtp_connector/model/smtp.py
tracardi_smtp_connector/model/__pycache__/smtp.cpython-38.pyc
tracardi_smtp_connector/service/sendman.py
tracardi_smtp_connector/service/__pycache__/sendman.cpython-38.pyc
tracardi_smtp_connector/test/test_plugin.py
tracardi_smtp_connector-0.6.0.dist-info/LICENSE.md
tracardi_smtp_connector-0.6.0.dist-info/METADATA
tracardi_smtp_connector-0.6.0.dist-info/WHEEL
tracardi_smtp_connector-0.6.0.dist-info/top_level.txt
tracardi_smtp_connector-0.6.0.dist-info/RECORD
