Metadata-Version: 2.1
Name: tracardi-smtp-connector
Version: 0.6.0
Summary: The purpose of this plugin is sending mail within Tracardi system.
Home-page: UNKNOWN
Author: Patryk Migaj
Author-email: patromi123@gmail.com
License: UNKNOWN
Keywords: tracardi,plugin
Platform: UNKNOWN
Classifier: Programming Language :: Python :: 3
Classifier: License :: OSI Approved :: MIT License
Classifier: Operating System :: OS Independent
Requires-Python: >=3.8
License-File: LICENSE.md
Requires-Dist: pydantic
Requires-Dist: beautifulsoup4
Requires-Dist: tracardi-plugin-sdk (>=0.6.21)
Requires-Dist: tracardi-dot-notation (>=0.6.4)
Requires-Dist: tracardi (>=0.6.18)
Requires-Dist: lxml
